README.txt
setup.cfg
setup.py
docs/HISTORY.txt
docs/INSTALL.txt
docs/LICENSE.GPL
docs/LICENSE.txt
zgeo/__init__.py
zgeo.plone.geographer.egg-info/PKG-INFO
zgeo.plone.geographer.egg-info/SOURCES.txt
zgeo.plone.geographer.egg-info/dependency_links.txt
zgeo.plone.geographer.egg-info/entry_points.txt
zgeo.plone.geographer.egg-info/namespace_packages.txt
zgeo.plone.geographer.egg-info/not-zip-safe
zgeo.plone.geographer.egg-info/requires.txt
zgeo.plone.geographer.egg-info/top_level.txt
zgeo/plone/__init__.py
zgeo/plone/geographer/README.txt
zgeo/plone/geographer/__init__.py
zgeo/plone/geographer/configure.zcml
zgeo/plone/geographer/event.py
zgeo/plone/geographer/setuphandlers.py
zgeo/plone/geographer/version.txt
zgeo/plone/geographer/Extensions/Install.py
zgeo/plone/geographer/Extensions/__init__.py
zgeo/plone/geographer/profiles/default/import_steps.xml
zgeo/plone/geographer/profiles/default/zgeo.plone.geographer_various.txt
zgeo/plone/geographer/tests/__init__.py
zgeo/plone/geographer/tests/base.py
zgeo/plone/geographer/tests/test_doctests.py
zgeo/plone/geographer/tests/test_setup.py
