Metadata-Version: 1.0
Name: zgeo.plone.geographer
Version: 0.1.1
Summary: Geographic annotation for Plone
Home-page: http://trac.gispython.org/projects/PrimaGIS/wiki/zgeo.plone.geographer
Author: Sean Gillies
Author-email: sgillies@frii.com
License: GPL
Keywords: gis geography geospatial plone
Platform: UNKNOWN
Classifier: Framework :: Plone
Classifier: Framework :: Zope2
Classifier: Framework :: Zope3
Classifier: Programming Language :: Python
Classifier: Topic :: Software Development :: Libraries :: Python Modules
Classifier: Topic :: Scientific/Engineering :: GIS
Classifier: Development Status :: 3 - Alpha
Classifier: Intended Audience :: Developers
